nc_user_manager/__init__.py
nc_user_manager/cache.py
nc_user_manager/client.py
nc_user_manager/exceptions.py
nc_user_manager/models.py
nc_user_manager/utils.py
nc_user_terminator-0.1.20.dist-info/METADATA
nc_user_terminator-0.1.20.dist-info/WHEEL
nc_user_terminator-0.1.20.dist-info/top_level.txt
nc_user_terminator-0.1.20.dist-info/RECORD
