Metadata-Version: 2.4
Name: nc-user-terminator
Version: 0.1.20
Summary: OAuth client wrapper for multi-tenant projects
Author: bw_song
Author-email: m132777096902@gmail.com
Requires-Python: >=3.8
Requires-Dist: cachetools==5.3.3
Dynamic: author-email
Dynamic: requires-python
